twiggy/__init__.py
twiggy/filters.py
twiggy/formats.py
twiggy/levels.py
twiggy/logger.py
twiggy/logging_compat.py
twiggy/message.py
twiggy/outputs.py
twiggy/features/__init__.py
twiggy/features/procinfo.py
twiggy/features/socket.py
twiggy/lib/__init__.py
twiggy/lib/converter.py
twiggy/lib/text.py
twiggy/lib/validators.py
Twiggy-0.5.1.dist-info/LICENSE
Twiggy-0.5.1.dist-info/METADATA
Twiggy-0.5.1.dist-info/WHEEL
Twiggy-0.5.1.dist-info/top_level.txt
Twiggy-0.5.1.dist-info/RECORD
