Metadata-Version: 2.1
Name: Twiggy
Version: 0.5.1
Summary: a Pythonic logger
Home-page: https://github.com/wearpants/twiggy/
Author: Pete Fein
Author-email: pete@wearpants.org
License: BSD
Platform: UNKNOWN
Classifier: Topic :: System :: Logging
Classifier: Development Status :: 5 - Production/Stable
Classifier: Intended Audience :: Developers
Classifier: Programming Language :: Python
Classifier: Programming Language :: Python :: 2
Classifier: Programming Language :: Python :: 2.7
Classifier: Programming Language :: Python :: 3
Classifier: Programming Language :: Python :: 3.5
Classifier: Programming Language :: Python :: 3.6
Classifier: Programming Language :: Python :: 3.7
Classifier: Programming Language :: Python :: 3.8
Classifier: Programming Language :: Python :: 3.9
Classifier: License :: OSI Approved :: BSD License
